LICENSE
MANIFEST.in
README.md
pyproject.toml
setup.py
pyVX2/__init__.py
pyVX2/avx2_ops.c
pyVX2/avx2_ops.pyx
pyvx2_sbhadade.egg-info/PKG-INFO
pyvx2_sbhadade.egg-info/SOURCES.txt
pyvx2_sbhadade.egg-info/dependency_links.txt
pyvx2_sbhadade.egg-info/not-zip-safe
pyvx2_sbhadade.egg-info/requires.txt
pyvx2_sbhadade.egg-info/top_level.txt
tests/test_avx2_ops.py