Metadata-Version: 2.4
Name: pyvx2-sbhadade
Version: 0.1.0
Summary: AVX2-accelerated array and matrix operations for Python
Home-page: https://github.com/yourusername/pyVX2
Author: Your Name
Author-email: your.email@example.com
License: MIT
Project-URL: Homepage, https://github.com/yourusername/pyVX2
Project-URL: Repository, https://github.com/yourusername/pyVX2
Keywords: avx2,simd,performance,numpy,matrix multiplication
Classifier: Development Status :: 4 - Beta
Classifier: Intended Audience :: Developers
Classifier: License :: OSI Approved :: MIT License
Classifier: Programming Language :: Python :: 3
Requires-Python: >=3.8
License-File: LICENSE
Requires-Dist: numpy>=1.19.0
Dynamic: author
Dynamic: author-email
Dynamic: home-page
Dynamic: license-file
Dynamic: requires-python
